ah_examples/__init__.py
ah_examples/hand_wave.py
ah_examples/observer_example.py
ah_examples/plot_motors.py
ah_examples/plot_motors_and_touch.py
ah_examples/plot_touch_sensors.py
ah_examples/send_misc_msg.py
ah_examples/simulated_hand_wave.py
ah_examples/speed_tests.py
ah_examples/validate_hand.py
ah_examples/write_registers.py
ah_plotting/__init__.py
ah_plotting/plots.py
ah_plotting/touch_sensor_legend_sml.png
ah_wrapper/__init__.py
ah_wrapper/ah_api.py
ah_wrapper/ah_parser.py
ah_wrapper/ah_serial_client.py
ah_wrapper/functions.py
ah_wrapper/hand.py
ah_wrapper/observer.py
ah_wrapper/ppp_stuffing.py
ah_wrapper/serial_connection.py
ah_wrapper/sim_functions.py
ah_wrapper/sim_serial.py
ah_wrapper/sim_serial_connection.py
ability_hand-0.2.2.dist-info/METADATA
ability_hand-0.2.2.dist-info/WHEEL
ability_hand-0.2.2.dist-info/entry_points.txt
ability_hand-0.2.2.dist-info/top_level.txt
ability_hand-0.2.2.dist-info/RECORD
