Metadata-Version: 2.4
Name: ability_hand
Version: 0.2.2
Summary: Python wrapper for the PSYONIC Ability Hand API
Home-page: https://github.com/psyonicinc/ability-hand-api
Author: Justin Francis
Author-email: jfrancis@psyonic.io
Project-URL: PSYONIC Website, https://psyonic.io
Project-URL: CHANGELOG, https://github.com/psyonicinc/ability-hand-api/blob/master/python/CHANGELOG.md
Classifier: Programming Language :: Python :: 3
Classifier: Operating System :: OS Independent
Requires-Python: >=3.10
Requires-Dist: pyserial>=3.5
Requires-Dist: matplotlib<=3.10.0,>=3.6.3
Dynamic: author
Dynamic: author-email
Dynamic: classifier
Dynamic: description
Dynamic: description-content-type
Dynamic: home-page
Dynamic: project-url
Dynamic: requires-dist
Dynamic: requires-python
Dynamic: summary
